switchtools/__init__.py
switchtools/switchcase.py
switchtools-1.4.dist-info/METADATA
switchtools-1.4.dist-info/WHEEL
switchtools-1.4.dist-info/top_level.txt
switchtools-1.4.dist-info/RECORD
